bumper/__init__.py
bumper/cars.py
bumper/utils.py
bumper_lib-2.0.4.dist-info/METADATA
bumper_lib-2.0.4.dist-info/RECORD
bumper_lib-2.0.4.dist-info/WHEEL
bumper_lib-2.0.4.dist-info/top_level.txt
