Metadata-Version: 2.1
Name: bumper-lib
Version: 2.0.4
Summary: A library to bump / pin your dependency requirements.
Home-page: https://github.com/maxzheng/bumper-lib
Author: Max Zheng
Author-email: maxzheng.os@gmail.com
License: MIT
Keywords: library bump pin requirements requirements.txt pinned.txt
Platform: UNKNOWN
Classifier: Development Status :: 5 - Production/Stable
Classifier: Intended Audience :: Developers
Classifier: Topic :: Software Development
Classifier: License :: OSI Approved :: MIT License
Classifier: Programming Language :: Python :: 2
Classifier: Programming Language :: Python :: 2.7
Classifier: Programming Language :: Python :: 3
Classifier: Programming Language :: Python :: 3.6
Requires-Dist: requests
Requires-Dist: simplejson
